odoo/addons/l10n_br_account_due_list/README.rst
odoo/addons/l10n_br_account_due_list/__init__.py
odoo/addons/l10n_br_account_due_list/__manifest__.py
odoo/addons/l10n_br_account_due_list/i18n/es.po
odoo/addons/l10n_br_account_due_list/i18n/l10n_br_account_due_list.pot
odoo/addons/l10n_br_account_due_list/i18n/pt_BR.po
odoo/addons/l10n_br_account_due_list/models/__init__.py
odoo/addons/l10n_br_account_due_list/models/account_move.py
odoo/addons/l10n_br_account_due_list/readme/CONFIGURE.md
odoo/addons/l10n_br_account_due_list/readme/CONTRIBUTORS.md
odoo/addons/l10n_br_account_due_list/readme/DESCRIPTION.md
odoo/addons/l10n_br_account_due_list/readme/HISTORY.md
odoo/addons/l10n_br_account_due_list/readme/INSTALL.md
odoo/addons/l10n_br_account_due_list/readme/ROADMAP.md
odoo/addons/l10n_br_account_due_list/readme/USAGE.md
odoo/addons/l10n_br_account_due_list/static/description/icon.png
odoo/addons/l10n_br_account_due_list/static/description/index.html
odoo/addons/l10n_br_account_due_list/static/img/l10n_br_account_due_list_payable.png
odoo/addons/l10n_br_account_due_list/static/img/l10n_br_account_due_list_receivable.png
odoo/addons/l10n_br_account_due_list/tests/__init__.py
odoo/addons/l10n_br_account_due_list/tests/test_payments.py
odoo/addons/l10n_br_account_due_list/views/account_move_view.xml
odoo_addon_l10n_br_account_due_list-18.0.1.0.0.4.dist-info/METADATA
odoo_addon_l10n_br_account_due_list-18.0.1.0.0.4.dist-info/WHEEL
odoo_addon_l10n_br_account_due_list-18.0.1.0.0.4.dist-info/top_level.txt
odoo_addon_l10n_br_account_due_list-18.0.1.0.0.4.dist-info/RECORD
